sht_sensor/__init__.py
sht_sensor/__main__.py
sht_sensor/gpio.py
sht_sensor/sensor.py
sht_sensor-18.4.2.dist-info/DESCRIPTION.rst
sht_sensor-18.4.2.dist-info/METADATA
sht_sensor-18.4.2.dist-info/RECORD
sht_sensor-18.4.2.dist-info/WHEEL
sht_sensor-18.4.2.dist-info/entry_points.txt
sht_sensor-18.4.2.dist-info/metadata.json
sht_sensor-18.4.2.dist-info/top_level.txt
