Metadata-Version: 2.0
Name: sht-sensor
Version: 18.4.2
Summary: Driver and command-line tool for Sensirion SHT1x and SHT7x sensors connected to GPIO pins.
Home-page: http://github.com/kizniche/sht-sensor
Author: Kyle Gabriel
Author-email: UNKNOWN
License: WTFPL
Keywords: sht sensor sensirion ic sht1x sht7x sht10 sht11 sht15 sht71 sht75 T temperature RH relative humidity dew point celsius environment conditioning measurement gpio hardware driver serial 2-wire crc8
Platform: UNKNOWN
Classifier: Development Status :: 4 - Beta
Classifier: Environment :: Console
Classifier: Intended Audience :: Developers
Classifier: Intended Audience :: End Users/Desktop
Classifier: Intended Audience :: Manufacturing
Classifier: Intended Audience :: System Administrators
Classifier: License :: Public Domain
Classifier: Operating System :: POSIX :: Linux
Classifier: Programming Language :: Python
Classifier: Programming Language :: Python :: 2.7
Classifier: Programming Language :: Python :: 3
Classifier: Programming Language :: Python :: 3.5
Classifier: Topic :: Home Automation
Classifier: Topic :: Scientific/Engineering :: Atmospheric Science
Classifier: Topic :: System :: Hardware :: Hardware Drivers
Classifier: Topic :: System :: Monitoring
Classifier: Topic :: System :: Operating System Kernels :: Linux
Classifier: Topic :: Utilities
